ts_pip_plugin/__init__.py
ts_pip_plugin/__main__.py
ts_pip_plugin/cli.py
ts_pip_plugin/scanner.py
ts_pip_plugin-1.0.3.data/scripts/ts-pip-plugin
ts_pip_plugin-1.0.3.dist-info/LICENSE
ts_pip_plugin-1.0.3.dist-info/METADATA
ts_pip_plugin-1.0.3.dist-info/WHEEL
ts_pip_plugin-1.0.3.dist-info/entry_points.txt
ts_pip_plugin-1.0.3.dist-info/top_level.txt
ts_pip_plugin-1.0.3.dist-info/RECORD
