Metadata-Version: 2.1
Name: ts-pip-plugin
Version: 1.0.3
Summary: Scans a Python project for all installed pip modules and posts the scan information to the TrustSource service or writes it to disc
Home-page: https://github.com/trustsource/ts-pip-plugin.git
Download-URL: 
Author: EACG GmbH
License: ASL-2.0
Keywords: scanning,dependencies,modules,compliance,TrustSource
Platform: UNKNOWN
License-File: LICENSE
Requires-Dist: ts-python-client (==1.0.3)
Requires-Dist: importlib-metadata
